membrain_pick/__init__.py
membrain_pick/orientation.py
membrain_pick/predict.py
membrain_pick/train.py
membrain_pick/cli/__init__.py
membrain_pick/cli/cli.py
membrain_pick/cli/convert_meshes_cli.py
membrain_pick/cli/mesh_conversion_cli.py
membrain_pick/cli/predict_cli.py
membrain_pick/cli/surforama_cli.py
membrain_pick/cli/train_cli.py
membrain_pick/cli/commands/__init__.py
membrain_pick/clustering/__init__.py
membrain_pick/clustering/mean_shift_inference.py
membrain_pick/clustering/mean_shift_membrainv1.py
membrain_pick/clustering/mean_shift_utils.py
membrain_pick/clustering/mean_shift_utils_membrainv1.py
membrain_pick/data_augmentations/__init__.py
membrain_pick/data_augmentations/augmentation_utils.py
membrain_pick/data_augmentations/pointcloud_augmentations.py
membrain_pick/data_augmentations/pointcloud_transforms.py
membrain_pick/dataloading/__init__.py
membrain_pick/dataloading/data_utils.py
membrain_pick/dataloading/diffusionnet_datamodule.py
membrain_pick/dataloading/diffusionnet_dataset.py
membrain_pick/dataloading/mempick_dataset.py
membrain_pick/dataloading/mesh_partitioning.py
membrain_pick/mesh_projections/__init__.py
membrain_pick/mesh_projections/bbox_utils.py
membrain_pick/mesh_projections/compute_mesh_projection.py
membrain_pick/mesh_projections/mesh_class.py
membrain_pick/mesh_projections/mesh_conversion_wrappers.py
membrain_pick/mesh_projections/mesh_projection.py
membrain_pick/mesh_projections/mesh_projection_utils.py
membrain_pick/napari_utils/__init__.py
membrain_pick/napari_utils/scalar_selection.py
membrain_pick/napari_utils/surforama_cli_utils.py
membrain_pick/networks/__init__.py
membrain_pick/networks/diffusion_net/__init__.py
membrain_pick/networks/diffusion_net/geometry.py
membrain_pick/networks/diffusion_net/layers.py
membrain_pick/networks/diffusion_net/ms_GPU_orig.py
membrain_pick/networks/diffusion_net/ms_batch_seed_orig.py
membrain_pick/networks/diffusion_net/ms_proposal.py
membrain_pick/networks/diffusion_net/utils.py
membrain_pick-0.0.7.dist-info/METADATA
membrain_pick-0.0.7.dist-info/WHEEL
membrain_pick-0.0.7.dist-info/entry_points.txt
membrain_pick-0.0.7.dist-info/RECORD
