Metadata-Version: 2.4
Name: membrain-pick
Version: 0.0.7
Summary: membrane protein localization for cryo-ET
Project-URL: homepage, https://github.com/teamtomo/membrain-seg
Project-URL: repository, https://github.com/teamtomo/membrain-seg
Author-email: Lorenz Lamm <lorenz.lamm@helmholtz-munich.de>
License: BSD 3-Clause License
Classifier: Development Status :: 3 - Alpha
Classifier: License :: OSI Approved :: BSD License
Classifier: Natural Language :: English
Classifier: Programming Language :: Python :: 3
Classifier: Programming Language :: Python :: 3.8
Classifier: Programming Language :: Python :: 3.9
Classifier: Programming Language :: Python :: 3.10
Classifier: Typing :: Typed
Requires-Python: >=3.8
Requires-Dist: h5py
Requires-Dist: lxml[html-clean]
Requires-Dist: membrain-seg
Requires-Dist: potpourri3d
Requires-Dist: pyacvd
Requires-Dist: pyqt5
Requires-Dist: pyvista
Requires-Dist: robust-laplacian
Requires-Dist: scikit-learn
Requires-Dist: scipy<1.12.1
Requires-Dist: starfile
Requires-Dist: trimesh
Requires-Dist: vtk
Provides-Extra: dev
Requires-Dist: black; extra == 'dev'
Requires-Dist: ipython; extra == 'dev'
Requires-Dist: mkdocs-material; extra == 'dev'
Requires-Dist: pdbpp; extra == 'dev'
Requires-Dist: pre-commit; extra == 'dev'
Requires-Dist: pytest; extra == 'dev'
Requires-Dist: pytest-cov; extra == 'dev'
Requires-Dist: rich; extra == 'dev'
Requires-Dist: ruff; extra == 'dev'
Provides-Extra: test
Requires-Dist: pytest-cov; extra == 'test'
Requires-Dist: pytest>=6.0; extra == 'test'
